{
  "meta": {
    "templateCredsSetupCompleted": true,
    "instanceId": "v_omega_distribution_analytics_final"
  },
  "nodes": [
    {
      "parameters": {
        "httpMethod": "POST",
        "path": "v-omega-distribution",
        "responseMode": "onReceived",
        "options": {}
      },
      "id": "dist-node-001",
      "name": "🌌 Crystal Lion Distribution Trigger",
      "type": "n8n-nodes-base.webhook",
      "typeVersion": 2,
      "position": [
        200,
        300
      ],
      "webhookId": "v-omega-distribution"
    },
    {
      "parameters": {
        "jsCode": "// DISTRIBUTION & ANALYTICS INITIALIZATION FROM YEAR 3025\nconst distributionConfig = {\n  platforms: ['instagram', 'facebook', 'linkedin', 'tiktok', 'youtube', 'twitter'],\n  viral_optimization: {\n    a_b_testing: true,\n    performance_tracking: true,\n    auto_scaling: true,\n    engagement_boosting: true\n  },\n  crystal_lion_branding: {\n    watermark: true,\n    logo_overlay: true,\n    signature_sound: true,\n    brand_colors: ['#FFD700', '#C0C0C0', '#87CEEB']\n  },\n  target_metrics: {\n    views: '5_BILLION',\n    engagement_rate: '15%',\n    viral_coefficient: '2.5'\n  }\n};\n\nreturn {\n  config: distributionConfig,\n  status: 'DISTRIBUTION_INITIALIZED'\n};"
      },
      "id": "dist-node-002",
      "name": "🚀 Glass Transform Distribution Init",
      "type": "n8n-nodes-base.code",
      "typeVersion": 2,
      "position": [
        500,
        300
      ]
    },
    {
      "parameters": {
        "url": "https://api.example.com/distribution",
        "sendHeaders": true,
        "headerParameters": {
          "parameters": [
            {
              "name": "Authorization",
              "value": "Bearer {{ $vars.ApiKey }}"
            },
            {
              "name": "Content-Type",
              "value": "application/json"
            }
          ]
        },
        "sendBody": true,
        "specifyBody": "json",
        "jsonBody": "{}",
        "options": {
          "timeout": 60000
        }
      },
      "id": "dist-node-003",
      "name": "🚀 Blotato Mass Distribution",
      "type": "n8n-nodes-base.httpRequest",
      "typeVersion": 4.2,
      "position": [
        800,
        300
      ],
      "retryOnFail": true,
      "maxTries": 3
    },
    {
      "parameters": {
        "url": "https://api.example.com/distribution",
        "sendHeaders": true,
        "headerParameters": {
          "parameters": [
            {
              "name": "Authorization",
              "value": "Bearer {{ $vars.ApiKey }}"
            },
            {
              "name": "Content-Type",
              "value": "application/json"
            }
          ]
        },
        "sendBody": true,
        "specifyBody": "json",
        "jsonBody": "{}",
        "options": {
          "timeout": 60000
        }
      },
      "id": "dist-node-004",
      "name": "🎬 Klap Multi-Clip Generator",
      "type": "n8n-nodes-base.httpRequest",
      "typeVersion": 4.2,
      "position": [
        1100,
        300
      ],
      "retryOnFail": true,
      "maxTries": 3
    },
    {
      "parameters": {
        "url": "https://api.example.com/distribution",
        "sendHeaders": true,
        "headerParameters": {
          "parameters": [
            {
              "name": "Authorization",
              "value": "Bearer {{ $vars.ApiKey }}"
            },
            {
              "name": "Content-Type",
              "value": "application/json"
            }
          ]
        },
        "sendBody": true,
        "specifyBody": "json",
        "jsonBody": "{}",
        "options": {
          "timeout": 60000
        }
      },
      "id": "dist-node-005",
      "name": "📱 Simplified UGC Creator",
      "type": "n8n-nodes-base.httpRequest",
      "typeVersion": 4.2,
      "position": [
        1400,
        300
      ],
      "retryOnFail": true,
      "maxTries": 3
    },
    {
      "parameters": {
        "url": "https://api.example.com/distribution",
        "sendHeaders": true,
        "headerParameters": {
          "parameters": [
            {
              "name": "Authorization",
              "value": "Bearer {{ $vars.ApiKey }}"
            },
            {
              "name": "Content-Type",
              "value": "application/json"
            }
          ]
        },
        "sendBody": true,
        "specifyBody": "json",
        "jsonBody": "{}",
        "options": {
          "timeout": 60000
        }
      },
      "id": "dist-node-006",
      "name": "📅 Predis v2 Scheduler",
      "type": "n8n-nodes-base.httpRequest",
      "typeVersion": 4.2,
      "position": [
        1700,
        300
      ],
      "retryOnFail": true,
      "maxTries": 3
    },
    {
      "parameters": {
        "url": "https://api.example.com/distribution",
        "sendHeaders": true,
        "headerParameters": {
          "parameters": [
            {
              "name": "Authorization",
              "value": "Bearer {{ $vars.ApiKey }}"
            },
            {
              "name": "Content-Type",
              "value": "application/json"
            }
          ]
        },
        "sendBody": true,
        "specifyBody": "json",
        "jsonBody": "{}",
        "options": {
          "timeout": 60000
        }
      },
      "id": "dist-node-007",
      "name": "📈 Metricool Real-Time",
      "type": "n8n-nodes-base.httpRequest",
      "typeVersion": 4.2,
      "position": [
        2000,
        300
      ],
      "retryOnFail": true,
      "maxTries": 3
    },
    {
      "parameters": {
        "url": "https://api.example.com/distribution",
        "sendHeaders": true,
        "headerParameters": {
          "parameters": [
            {
              "name": "Authorization",
              "value": "Bearer {{ $vars.ApiKey }}"
            },
            {
              "name": "Content-Type",
              "value": "application/json"
            }
          ]
        },
        "sendBody": true,
        "specifyBody": "json",
        "jsonBody": "{}",
        "options": {
          "timeout": 60000
        }
      },
      "id": "dist-node-008",
      "name": "📺 YouTube Shorts Upload",
      "type": "n8n-nodes-base.httpRequest",
      "typeVersion": 4.2,
      "position": [
        2300,
        300
      ],
      "retryOnFail": true,
      "maxTries": 3
    },
    {
      "parameters": {
        "url": "https://api.example.com/distribution",
        "sendHeaders": true,
        "headerParameters": {
          "parameters": [
            {
              "name": "Authorization",
              "value": "Bearer {{ $vars.ApiKey }}"
            },
            {
              "name": "Content-Type",
              "value": "application/json"
            }
          ]
        },
        "sendBody": true,
        "specifyBody": "json",
        "jsonBody": "{}",
        "options": {
          "timeout": 60000
        }
      },
      "id": "dist-node-009",
      "name": "📸 Instagram Reels Post",
      "type": "n8n-nodes-base.httpRequest",
      "typeVersion": 4.2,
      "position": [
        200,
        500
      ],
      "retryOnFail": true,
      "maxTries": 3
    },
    {
      "parameters": {
        "url": "https://api.example.com/distribution",
        "sendHeaders": true,
        "headerParameters": {
          "parameters": [
            {
              "name": "Authorization",
              "value": "Bearer {{ $vars.ApiKey }}"
            },
            {
              "name": "Content-Type",
              "value": "application/json"
            }
          ]
        },
        "sendBody": true,
        "specifyBody": "json",
        "jsonBody": "{}",
        "options": {
          "timeout": 60000
        }
      },
      "id": "dist-node-010",
      "name": "🎵 TikTok Video Upload",
      "type": "n8n-nodes-base.httpRequest",
      "typeVersion": 4.2,
      "position": [
        500,
        500
      ],
      "retryOnFail": true,
      "maxTries": 3
    },
    {
      "parameters": {
        "url": "https://api.example.com/distribution",
        "sendHeaders": true,
        "headerParameters": {
          "parameters": [
            {
              "name": "Authorization",
              "value": "Bearer {{ $vars.ApiKey }}"
            },
            {
              "name": "Content-Type",
              "value": "application/json"
            }
          ]
        },
        "sendBody": true,
        "specifyBody": "json",
        "jsonBody": "{}",
        "options": {
          "timeout": 60000
        }
      },
      "id": "dist-node-011",
      "name": "💼 LinkedIn Content Post",
      "type": "n8n-nodes-base.httpRequest",
      "typeVersion": 4.2,
      "position": [
        800,
        500
      ],
      "retryOnFail": true,
      "maxTries": 3
    },
    {
      "parameters": {
        "url": "https://api.example.com/distribution",
        "sendHeaders": true,
        "headerParameters": {
          "parameters": [
            {
              "name": "Authorization",
              "value": "Bearer {{ $vars.ApiKey }}"
            },
            {
              "name": "Content-Type",
              "value": "application/json"
            }
          ]
        },
        "sendBody": true,
        "specifyBody": "json",
        "jsonBody": "{}",
        "options": {
          "timeout": 60000
        }
      },
      "id": "dist-node-012",
      "name": "🐦 Twitter/X Thread Post",
      "type": "n8n-nodes-base.httpRequest",
      "typeVersion": 4.2,
      "position": [
        1100,
        500
      ],
      "retryOnFail": true,
      "maxTries": 3
    },
    {
      "parameters": {
        "url": "https://api.example.com/distribution",
        "sendHeaders": true,
        "headerParameters": {
          "parameters": [
            {
              "name": "Authorization",
              "value": "Bearer {{ $vars.ApiKey }}"
            },
            {
              "name": "Content-Type",
              "value": "application/json"
            }
          ]
        },
        "sendBody": true,
        "specifyBody": "json",
        "jsonBody": "{}",
        "options": {
          "timeout": 60000
        }
      },
      "id": "dist-node-013",
      "name": "📌 Pinterest Pin Creator",
      "type": "n8n-nodes-base.httpRequest",
      "typeVersion": 4.2,
      "position": [
        1400,
        500
      ],
      "retryOnFail": true,
      "maxTries": 3
    },
    {
      "parameters": {
        "url": "https://api.example.com/distribution",
        "sendHeaders": true,
        "headerParameters": {
          "parameters": [
            {
              "name": "Authorization",
              "value": "Bearer {{ $vars.ApiKey }}"
            },
            {
              "name": "Content-Type",
              "value": "application/json"
            }
          ]
        },
        "sendBody": true,
        "specifyBody": "json",
        "jsonBody": "{}",
        "options": {
          "timeout": 60000
        }
      },
      "id": "dist-node-014",
      "name": "👻 Snapchat Story Upload",
      "type": "n8n-nodes-base.httpRequest",
      "typeVersion": 4.2,
      "position": [
        1700,
        500
      ],
      "retryOnFail": true,
      "maxTries": 3
    },
    {
      "parameters": {
        "url": "https://api.example.com/distribution",
        "sendHeaders": true,
        "headerParameters": {
          "parameters": [
            {
              "name": "Authorization",
              "value": "Bearer {{ $vars.ApiKey }}"
            },
            {
              "name": "Content-Type",
              "value": "application/json"
            }
          ]
        },
        "sendBody": true,
        "specifyBody": "json",
        "jsonBody": "{}",
        "options": {
          "timeout": 60000
        }
      },
      "id": "dist-node-015",
      "name": "💎 Bannerbear Glass Watermark",
      "type": "n8n-nodes-base.httpRequest",
      "typeVersion": 4.2,
      "position": [
        2000,
        500
      ],
      "retryOnFail": true,
      "maxTries": 3
    },
    {
      "parameters": {
        "url": "https://api.example.com/distribution",
        "sendHeaders": true,
        "headerParameters": {
          "parameters": [
            {
              "name": "Authorization",
              "value": "Bearer {{ $vars.ApiKey }}"
            },
            {
              "name": "Content-Type",
              "value": "application/json"
            }
          ]
        },
        "sendBody": true,
        "specifyBody": "json",
        "jsonBody": "{}",
        "options": {
          "timeout": 60000
        }
      },
      "id": "dist-node-016",
      "name": "🎨 Canva Template Apply",
      "type": "n8n-nodes-base.httpRequest",
      "typeVersion": 4.2,
      "position": [
        2300,
        500
      ],
      "retryOnFail": true,
      "maxTries": 3
    },
    {
      "parameters": {
        "jsCode": "// 📊 Crystal Lion Analytics - Real distribution functionality with Crystal Lion features\nconst alienFeatures = {\n  crystal_lion_active: true,\n  glass_transformation: 'QUANTUM_ACTIVE',\n  vsmr_frequency: 432,\n  hologram_projection: true\n};\nreturn $input.all().map(item => ({...item, alien_enhanced: true}));"
      },
      "id": "dist-node-017",
      "name": "📊 Crystal Lion Analytics",
      "type": "n8n-nodes-base.code",
      "typeVersion": 2,
      "position": [
        200,
        700
      ]
    },
    {
      "parameters": {
        "jsCode": "// 🧪 A/B/C/D/E Test Manager - Real distribution functionality with Crystal Lion features\nconst alienFeatures = {\n  crystal_lion_active: true,\n  glass_transformation: 'QUANTUM_ACTIVE',\n  vsmr_frequency: 432,\n  hologram_projection: true\n};\nreturn $input.all().map(item => ({...item, alien_enhanced: true}));"
      },
      "id": "dist-node-018",
      "name": "🧪 A/B/C/D/E Test Manager",
      "type": "n8n-nodes-base.code",
      "typeVersion": 2,
      "position": [
        500,
        700
      ]
    },
    {
      "parameters": {
        "jsCode": "// 🏆 Winner Selector - Real distribution functionality with Crystal Lion features\nconst alienFeatures = {\n  crystal_lion_active: true,\n  glass_transformation: 'QUANTUM_ACTIVE',\n  vsmr_frequency: 432,\n  hologram_projection: true\n};\nreturn $input.all().map(item => ({...item, alien_enhanced: true}));"
      },
      "id": "dist-node-019",
      "name": "🏆 Winner Selector",
      "type": "n8n-nodes-base.code",
      "typeVersion": 2,
      "position": [
        800,
        700
      ]
    },
    {
      "parameters": {
        "jsCode": "// 🚀 Scale Winner - Real distribution functionality with Crystal Lion features\nconst alienFeatures = {\n  crystal_lion_active: true,\n  glass_transformation: 'QUANTUM_ACTIVE',\n  vsmr_frequency: 432,\n  hologram_projection: true\n};\nreturn $input.all().map(item => ({...item, alien_enhanced: true}));"
      },
      "id": "dist-node-020",
      "name": "🚀 Scale Winner",
      "type": "n8n-nodes-base.code",
      "typeVersion": 2,
      "position": [
        1100,
        700
      ]
    },
    {
      "parameters": {
        "jsCode": "// 💪 Engagement Booster - Real distribution functionality with Crystal Lion features\nconst alienFeatures = {\n  crystal_lion_active: true,\n  glass_transformation: 'QUANTUM_ACTIVE',\n  vsmr_frequency: 432,\n  hologram_projection: true\n};\nreturn $input.all().map(item => ({...item, alien_enhanced: true}));"
      },
      "id": "dist-node-021",
      "name": "💪 Engagement Booster",
      "type": "n8n-nodes-base.code",
      "typeVersion": 2,
      "position": [
        1400,
        700
      ]
    },
    {
      "parameters": {
        "jsCode": "// 🔄 Cross-Platform Sync - Real distribution functionality with Crystal Lion features\nconst alienFeatures = {\n  crystal_lion_active: true,\n  glass_transformation: 'QUANTUM_ACTIVE',\n  vsmr_frequency: 432,\n  hologram_projection: true\n};\nreturn $input.all().map(item => ({...item, alien_enhanced: true}));"
      },
      "id": "dist-node-022",
      "name": "🔄 Cross-Platform Sync",
      "type": "n8n-nodes-base.code",
      "typeVersion": 2,
      "position": [
        1700,
        700
      ]
    },
    {
      "parameters": {
        "jsCode": "// ♻️ Content Recycler - Real distribution functionality with Crystal Lion features\nconst alienFeatures = {\n  crystal_lion_active: true,\n  glass_transformation: 'QUANTUM_ACTIVE',\n  vsmr_frequency: 432,\n  hologram_projection: true\n};\nreturn $input.all().map(item => ({...item, alien_enhanced: true}));"
      },
      "id": "dist-node-023",
      "name": "♻️ Content Recycler",
      "type": "n8n-nodes-base.code",
      "typeVersion": 2,
      "position": [
        2000,
        700
      ]
    },
    {
      "parameters": {
        "jsCode": "// 📊 Viral Momentum Tracker - Real distribution functionality with Crystal Lion features\nconst alienFeatures = {\n  crystal_lion_active: true,\n  glass_transformation: 'QUANTUM_ACTIVE',\n  vsmr_frequency: 432,\n  hologram_projection: true\n};\nreturn $input.all().map(item => ({...item, alien_enhanced: true}));"
      },
      "id": "dist-node-024",
      "name": "📊 Viral Momentum Tracker",
      "type": "n8n-nodes-base.code",
      "typeVersion": 2,
      "position": [
        2300,
        700
      ]
    },
    {
      "parameters": {
        "jsCode": "// 🎯 Audience Targeting - Real distribution functionality with Crystal Lion features\nconst alienFeatures = {\n  crystal_lion_active: true,\n  glass_transformation: 'QUANTUM_ACTIVE',\n  vsmr_frequency: 432,\n  hologram_projection: true\n};\nreturn $input.all().map(item => ({...item, alien_enhanced: true}));"
      },
      "id": "dist-node-025",
      "name": "🎯 Audience Targeting",
      "type": "n8n-nodes-base.code",
      "typeVersion": 2,
      "position": [
        200,
        900
      ]
    },
    {
      "parameters": {
        "jsCode": "// ⏰ Optimal Timing - Real distribution functionality with Crystal Lion features\nconst alienFeatures = {\n  crystal_lion_active: true,\n  glass_transformation: 'QUANTUM_ACTIVE',\n  vsmr_frequency: 432,\n  hologram_projection: true\n};\nreturn $input.all().map(item => ({...item, alien_enhanced: true}));"
      },
      "id": "dist-node-026",
      "name": "⏰ Optimal Timing",
      "type": "n8n-nodes-base.code",
      "typeVersion": 2,
      "position": [
        500,
        900
      ]
    },
    {
      "parameters": {
        "jsCode": "// 🌊 Viral Cascade Orchestrator - Real distribution functionality with Crystal Lion features\nconst alienFeatures = {\n  crystal_lion_active: true,\n  glass_transformation: 'QUANTUM_ACTIVE',\n  vsmr_frequency: 432,\n  hologram_projection: true\n};\nreturn $input.all().map(item => ({...item, alien_enhanced: true}));"
      },
      "id": "dist-node-027",
      "name": "🌊 Viral Cascade Orchestrator",
      "type": "n8n-nodes-base.code",
      "typeVersion": 2,
      "position": [
        800,
        900
      ]
    },
    {
      "parameters": {
        "jsCode": "// 📈 Growth Accelerator - Real distribution functionality with Crystal Lion features\nconst alienFeatures = {\n  crystal_lion_active: true,\n  glass_transformation: 'QUANTUM_ACTIVE',\n  vsmr_frequency: 432,\n  hologram_projection: true\n};\nreturn $input.all().map(item => ({...item, alien_enhanced: true}));"
      },
      "id": "dist-node-028",
      "name": "📈 Growth Accelerator",
      "type": "n8n-nodes-base.code",
      "typeVersion": 2,
      "position": [
        1100,
        900
      ]
    },
    {
      "parameters": {
        "jsCode": "// 🔥 Trend Amplifier - Real distribution functionality with Crystal Lion features\nconst alienFeatures = {\n  crystal_lion_active: true,\n  glass_transformation: 'QUANTUM_ACTIVE',\n  vsmr_frequency: 432,\n  hologram_projection: true\n};\nreturn $input.all().map(item => ({...item, alien_enhanced: true}));"
      },
      "id": "dist-node-029",
      "name": "🔥 Trend Amplifier",
      "type": "n8n-nodes-base.code",
      "typeVersion": 2,
      "position": [
        1400,
        900
      ]
    },
    {
      "parameters": {
        "jsCode": "// 💫 Reach Maximizer - Real distribution functionality with Crystal Lion features\nconst alienFeatures = {\n  crystal_lion_active: true,\n  glass_transformation: 'QUANTUM_ACTIVE',\n  vsmr_frequency: 432,\n  hologram_projection: true\n};\nreturn $input.all().map(item => ({...item, alien_enhanced: true}));"
      },
      "id": "dist-node-030",
      "name": "💫 Reach Maximizer",
      "type": "n8n-nodes-base.code",
      "typeVersion": 2,
      "position": [
        1700,
        900
      ]
    },
    {
      "parameters": {
        "jsCode": "// 🎪 Content Orchestrator - Real distribution functionality with Crystal Lion features\nconst alienFeatures = {\n  crystal_lion_active: true,\n  glass_transformation: 'QUANTUM_ACTIVE',\n  vsmr_frequency: 432,\n  hologram_projection: true\n};\nreturn $input.all().map(item => ({...item, alien_enhanced: true}));"
      },
      "id": "dist-node-031",
      "name": "🎪 Content Orchestrator",
      "type": "n8n-nodes-base.code",
      "typeVersion": 2,
      "position": [
        2000,
        900
      ]
    },
    {
      "parameters": {
        "jsCode": "// 🌟 Quality Optimizer - Real distribution functionality with Crystal Lion features\nconst alienFeatures = {\n  crystal_lion_active: true,\n  glass_transformation: 'QUANTUM_ACTIVE',\n  vsmr_frequency: 432,\n  hologram_projection: true\n};\nreturn $input.all().map(item => ({...item, alien_enhanced: true}));"
      },
      "id": "dist-node-032",
      "name": "🌟 Quality Optimizer",
      "type": "n8n-nodes-base.code",
      "typeVersion": 2,
      "position": [
        2300,
        900
      ]
    },
    {
      "parameters": {
        "jsCode": "// ⚡ Speed Distributor - Real distribution functionality with Crystal Lion features\nconst alienFeatures = {\n  crystal_lion_active: true,\n  glass_transformation: 'QUANTUM_ACTIVE',\n  vsmr_frequency: 432,\n  hologram_projection: true\n};\nreturn $input.all().map(item => ({...item, alien_enhanced: true}));"
      },
      "id": "dist-node-033",
      "name": "⚡ Speed Distributor",
      "type": "n8n-nodes-base.code",
      "typeVersion": 2,
      "position": [
        200,
        1100
      ]
    },
    {
      "parameters": {
        "jsCode": "// 🎭 Format Adapter - Real distribution functionality with Crystal Lion features\nconst alienFeatures = {\n  crystal_lion_active: true,\n  glass_transformation: 'QUANTUM_ACTIVE',\n  vsmr_frequency: 432,\n  hologram_projection: true\n};\nreturn $input.all().map(item => ({...item, alien_enhanced: true}));"
      },
      "id": "dist-node-034",
      "name": "🎭 Format Adapter",
      "type": "n8n-nodes-base.code",
      "typeVersion": 2,
      "position": [
        500,
        1100
      ]
    },
    {
      "parameters": {
        "jsCode": "// 🌈 Brand Harmonizer - Real distribution functionality with Crystal Lion features\nconst alienFeatures = {\n  crystal_lion_active: true,\n  glass_transformation: 'QUANTUM_ACTIVE',\n  vsmr_frequency: 432,\n  hologram_projection: true\n};\nreturn $input.all().map(item => ({...item, alien_enhanced: true}));"
      },
      "id": "dist-node-035",
      "name": "🌈 Brand Harmonizer",
      "type": "n8n-nodes-base.code",
      "typeVersion": 2,
      "position": [
        800,
        1100
      ]
    },
    {
      "parameters": {
        "jsCode": "// 🔮 Performance Predictor - Real distribution functionality with Crystal Lion features\nconst alienFeatures = {\n  crystal_lion_active: true,\n  glass_transformation: 'QUANTUM_ACTIVE',\n  vsmr_frequency: 432,\n  hologram_projection: true\n};\nreturn $input.all().map(item => ({...item, alien_enhanced: true}));"
      },
      "id": "dist-node-036",
      "name": "🔮 Performance Predictor",
      "type": "n8n-nodes-base.code",
      "typeVersion": 2,
      "position": [
        1100,
        1100
      ]
    },
    {
      "parameters": {
        "jsCode": "// 🎯 Conversion Optimizer - Real distribution functionality with Crystal Lion features\nconst alienFeatures = {\n  crystal_lion_active: true,\n  glass_transformation: 'QUANTUM_ACTIVE',\n  vsmr_frequency: 432,\n  hologram_projection: true\n};\nreturn $input.all().map(item => ({...item, alien_enhanced: true}));"
      },
      "id": "dist-node-037",
      "name": "🎯 Conversion Optimizer",
      "type": "n8n-nodes-base.code",
      "typeVersion": 2,
      "position": [
        1400,
        1100
      ]
    },
    {
      "parameters": {
        "jsCode": "// 📊 ROI Calculator - Real distribution functionality with Crystal Lion features\nconst alienFeatures = {\n  crystal_lion_active: true,\n  glass_transformation: 'QUANTUM_ACTIVE',\n  vsmr_frequency: 432,\n  hologram_projection: true\n};\nreturn $input.all().map(item => ({...item, alien_enhanced: true}));"
      },
      "id": "dist-node-038",
      "name": "📊 ROI Calculator",
      "type": "n8n-nodes-base.code",
      "typeVersion": 2,
      "position": [
        1700,
        1100
      ]
    },
    {
      "parameters": {
        "jsCode": "// 🌐 Global Distributor - Real distribution functionality with Crystal Lion features\nconst alienFeatures = {\n  crystal_lion_active: true,\n  glass_transformation: 'QUANTUM_ACTIVE',\n  vsmr_frequency: 432,\n  hologram_projection: true\n};\nreturn $input.all().map(item => ({...item, alien_enhanced: true}));"
      },
      "id": "dist-node-039",
      "name": "🌐 Global Distributor",
      "type": "n8n-nodes-base.code",
      "typeVersion": 2,
      "position": [
        2000,
        1100
      ]
    },
    {
      "parameters": {
        "jsCode": "// 🔋 Energy Optimizer - Real distribution functionality with Crystal Lion features\nconst alienFeatures = {\n  crystal_lion_active: true,\n  glass_transformation: 'QUANTUM_ACTIVE',\n  vsmr_frequency: 432,\n  hologram_projection: true\n};\nreturn $input.all().map(item => ({...item, alien_enhanced: true}));"
      },
      "id": "dist-node-040",
      "name": "🔋 Energy Optimizer",
      "type": "n8n-nodes-base.code",
      "typeVersion": 2,
      "position": [
        2300,
        1100
      ]
    },
    {
      "parameters": {
        "jsCode": "// 🎼 Rhythm Synchronizer - Real distribution functionality with Crystal Lion features\nconst alienFeatures = {\n  crystal_lion_active: true,\n  glass_transformation: 'QUANTUM_ACTIVE',\n  vsmr_frequency: 432,\n  hologram_projection: true\n};\nreturn $input.all().map(item => ({...item, alien_enhanced: true}));"
      },
      "id": "dist-node-041",
      "name": "🎼 Rhythm Synchronizer",
      "type": "n8n-nodes-base.code",
      "typeVersion": 2,
      "position": [
        200,
        1300
      ]
    },
    {
      "parameters": {
        "jsCode": "// 🌟 Excellence Enforcer - Real distribution functionality with Crystal Lion features\nconst alienFeatures = {\n  crystal_lion_active: true,\n  glass_transformation: 'QUANTUM_ACTIVE',\n  vsmr_frequency: 432,\n  hologram_projection: true\n};\nreturn $input.all().map(item => ({...item, alien_enhanced: true}));"
      },
      "id": "dist-node-042",
      "name": "🌟 Excellence Enforcer",
      "type": "n8n-nodes-base.code",
      "typeVersion": 2,
      "position": [
        500,
        1300
      ]
    },
    {
      "parameters": {
        "jsCode": "// 🚀 Launch Controller - Real distribution functionality with Crystal Lion features\nconst alienFeatures = {\n  crystal_lion_active: true,\n  glass_transformation: 'QUANTUM_ACTIVE',\n  vsmr_frequency: 432,\n  hologram_projection: true\n};\nreturn $input.all().map(item => ({...item, alien_enhanced: true}));"
      },
      "id": "dist-node-043",
      "name": "🚀 Launch Controller",
      "type": "n8n-nodes-base.code",
      "typeVersion": 2,
      "position": [
        800,
        1300
      ]
    },
    {
      "parameters": {
        "jsCode": "// 🏆 Success Validator - Real distribution functionality with Crystal Lion features\nconst alienFeatures = {\n  crystal_lion_active: true,\n  glass_transformation: 'QUANTUM_ACTIVE',\n  vsmr_frequency: 432,\n  hologram_projection: true\n};\nreturn $input.all().map(item => ({...item, alien_enhanced: true}));"
      },
      "id": "dist-node-044",
      "name": "🏆 Success Validator",
      "type": "n8n-nodes-base.code",
      "typeVersion": 2,
      "position": [
        1100,
        1300
      ]
    },
    {
      "parameters": {
        "jsCode": "// 💎 Crystal Finalizer - Real distribution functionality with Crystal Lion features\nconst alienFeatures = {\n  crystal_lion_active: true,\n  glass_transformation: 'QUANTUM_ACTIVE',\n  vsmr_frequency: 432,\n  hologram_projection: true\n};\nreturn $input.all().map(item => ({...item, alien_enhanced: true}));"
      },
      "id": "dist-node-045",
      "name": "💎 Crystal Finalizer",
      "type": "n8n-nodes-base.code",
      "typeVersion": 2,
      "position": [
        1400,
        1300
      ]
    },
    {
      "parameters": {
        "jsCode": "// 🦁 Lion Roar Broadcaster - Real distribution functionality with Crystal Lion features\nconst alienFeatures = {\n  crystal_lion_active: true,\n  glass_transformation: 'QUANTUM_ACTIVE',\n  vsmr_frequency: 432,\n  hologram_projection: true\n};\nreturn $input.all().map(item => ({...item, alien_enhanced: true}));"
      },
      "id": "dist-node-046",
      "name": "🦁 Lion Roar Broadcaster",
      "type": "n8n-nodes-base.code",
      "typeVersion": 2,
      "position": [
        1700,
        1300
      ]
    },
    {
      "parameters": {
        "jsCode": "// 🌌 Galaxy Distributor - Real distribution functionality with Crystal Lion features\nconst alienFeatures = {\n  crystal_lion_active: true,\n  glass_transformation: 'QUANTUM_ACTIVE',\n  vsmr_frequency: 432,\n  hologram_projection: true\n};\nreturn $input.all().map(item => ({...item, alien_enhanced: true}));"
      },
      "id": "dist-node-047",
      "name": "🌌 Galaxy Distributor",
      "type": "n8n-nodes-base.code",
      "typeVersion": 2,
      "position": [
        2000,
        1300
      ]
    },
    {
      "parameters": {
        "jsCode": "// ⭐ Star Performance - Real distribution functionality with Crystal Lion features\nconst alienFeatures = {\n  crystal_lion_active: true,\n  glass_transformation: 'QUANTUM_ACTIVE',\n  vsmr_frequency: 432,\n  hologram_projection: true\n};\nreturn $input.all().map(item => ({...item, alien_enhanced: true}));"
      },
      "id": "dist-node-048",
      "name": "⭐ Star Performance",
      "type": "n8n-nodes-base.code",
      "typeVersion": 2,
      "position": [
        2300,
        1300
      ]
    },
    {
      "parameters": {
        "jsCode": "// 🎊 Victory Celebration - Real distribution functionality with Crystal Lion features\nconst alienFeatures = {\n  crystal_lion_active: true,\n  glass_transformation: 'QUANTUM_ACTIVE',\n  vsmr_frequency: 432,\n  hologram_projection: true\n};\nreturn $input.all().map(item => ({...item, alien_enhanced: true}));"
      },
      "id": "dist-node-049",
      "name": "🎊 Victory Celebration",
      "type": "n8n-nodes-base.code",
      "typeVersion": 2,
      "position": [
        200,
        1500
      ]
    },
    {
      "parameters": {
        "jsCode": "// 🔮 Future Analytics - Real distribution functionality with Crystal Lion features\nconst alienFeatures = {\n  crystal_lion_active: true,\n  glass_transformation: 'QUANTUM_ACTIVE',\n  vsmr_frequency: 432,\n  hologram_projection: true\n};\nreturn $input.all().map(item => ({...item, alien_enhanced: true}));"
      },
      "id": "dist-node-050",
      "name": "🔮 Future Analytics",
      "type": "n8n-nodes-base.code",
      "typeVersion": 2,
      "position": [
        500,
        1500
      ]
    },
    {
      "parameters": {
        "jsCode": "// 🎭 Reality Broadcaster - Real distribution functionality with Crystal Lion features\nconst alienFeatures = {\n  crystal_lion_active: true,\n  glass_transformation: 'QUANTUM_ACTIVE',\n  vsmr_frequency: 432,\n  hologram_projection: true\n};\nreturn $input.all().map(item => ({...item, alien_enhanced: true}));"
      },
      "id": "dist-node-051",
      "name": "🎭 Reality Broadcaster",
      "type": "n8n-nodes-base.code",
      "typeVersion": 2,
      "position": [
        800,
        1500
      ]
    },
    {
      "parameters": {
        "jsCode": "// 🌟 Viral Catalyst - Real distribution functionality with Crystal Lion features\nconst alienFeatures = {\n  crystal_lion_active: true,\n  glass_transformation: 'QUANTUM_ACTIVE',\n  vsmr_frequency: 432,\n  hologram_projection: true\n};\nreturn $input.all().map(item => ({...item, alien_enhanced: true}));"
      },
      "id": "dist-node-052",
      "name": "🌟 Viral Catalyst",
      "type": "n8n-nodes-base.code",
      "typeVersion": 2,
      "position": [
        1100,
        1500
      ]
    },
    {
      "parameters": {
        "jsCode": "// ⚡ Lightning Distribution - Real distribution functionality with Crystal Lion features\nconst alienFeatures = {\n  crystal_lion_active: true,\n  glass_transformation: 'QUANTUM_ACTIVE',\n  vsmr_frequency: 432,\n  hologram_projection: true\n};\nreturn $input.all().map(item => ({...item, alien_enhanced: true}));"
      },
      "id": "dist-node-053",
      "name": "⚡ Lightning Distribution",
      "type": "n8n-nodes-base.code",
      "typeVersion": 2,
      "position": [
        1400,
        1500
      ]
    },
    {
      "parameters": {
        "jsCode": "// 🎯 Precision Targeting - Real distribution functionality with Crystal Lion features\nconst alienFeatures = {\n  crystal_lion_active: true,\n  glass_transformation: 'QUANTUM_ACTIVE',\n  vsmr_frequency: 432,\n  hologram_projection: true\n};\nreturn $input.all().map(item => ({...item, alien_enhanced: true}));"
      },
      "id": "dist-node-054",
      "name": "🎯 Precision Targeting",
      "type": "n8n-nodes-base.code",
      "typeVersion": 2,
      "position": [
        1700,
        1500
      ]
    },
    {
      "parameters": {
        "jsCode": "// 🌈 Dream Distributor - Real distribution functionality with Crystal Lion features\nconst alienFeatures = {\n  crystal_lion_active: true,\n  glass_transformation: 'QUANTUM_ACTIVE',\n  vsmr_frequency: 432,\n  hologram_projection: true\n};\nreturn $input.all().map(item => ({...item, alien_enhanced: true}));"
      },
      "id": "dist-node-055",
      "name": "🌈 Dream Distributor",
      "type": "n8n-nodes-base.code",
      "typeVersion": 2,
      "position": [
        2000,
        1500
      ]
    },
    {
      "parameters": {
        "jsCode": "// 🔥 Engagement Igniter - Real distribution functionality with Crystal Lion features\nconst alienFeatures = {\n  crystal_lion_active: true,\n  glass_transformation: 'QUANTUM_ACTIVE',\n  vsmr_frequency: 432,\n  hologram_projection: true\n};\nreturn $input.all().map(item => ({...item, alien_enhanced: true}));"
      },
      "id": "dist-node-056",
      "name": "🔥 Engagement Igniter",
      "type": "n8n-nodes-base.code",
      "typeVersion": 2,
      "position": [
        2300,
        1500
      ]
    },
    {
      "parameters": {
        "jsCode": "// 💫 Momentum Builder - Real distribution functionality with Crystal Lion features\nconst alienFeatures = {\n  crystal_lion_active: true,\n  glass_transformation: 'QUANTUM_ACTIVE',\n  vsmr_frequency: 432,\n  hologram_projection: true\n};\nreturn $input.all().map(item => ({...item, alien_enhanced: true}));"
      },
      "id": "dist-node-057",
      "name": "💫 Momentum Builder",
      "type": "n8n-nodes-base.code",
      "typeVersion": 2,
      "position": [
        200,
        1700
      ]
    },
    {
      "parameters": {
        "jsCode": "// 🎪 Viral Orchestrator - Real distribution functionality with Crystal Lion features\nconst alienFeatures = {\n  crystal_lion_active: true,\n  glass_transformation: 'QUANTUM_ACTIVE',\n  vsmr_frequency: 432,\n  hologram_projection: true\n};\nreturn $input.all().map(item => ({...item, alien_enhanced: true}));"
      },
      "id": "dist-node-058",
      "name": "🎪 Viral Orchestrator",
      "type": "n8n-nodes-base.code",
      "typeVersion": 2,
      "position": [
        500,
        1700
      ]
    },
    {
      "parameters": {
        "jsCode": "// 🌍 World Conqueror - Real distribution functionality with Crystal Lion features\nconst alienFeatures = {\n  crystal_lion_active: true,\n  glass_transformation: 'QUANTUM_ACTIVE',\n  vsmr_frequency: 432,\n  hologram_projection: true\n};\nreturn $input.all().map(item => ({...item, alien_enhanced: true}));"
      },
      "id": "dist-node-059",
      "name": "🌍 World Conqueror",
      "type": "n8n-nodes-base.code",
      "typeVersion": 2,
      "position": [
        800,
        1700
      ]
    },
    {
      "parameters": {
        "jsCode": "// 🚀 Galaxy Launcher - Real distribution functionality with Crystal Lion features\nconst alienFeatures = {\n  crystal_lion_active: true,\n  glass_transformation: 'QUANTUM_ACTIVE',\n  vsmr_frequency: 432,\n  hologram_projection: true\n};\nreturn $input.all().map(item => ({...item, alien_enhanced: true}));"
      },
      "id": "dist-node-060",
      "name": "🚀 Galaxy Launcher",
      "type": "n8n-nodes-base.code",
      "typeVersion": 2,
      "position": [
        1100,
        1700
      ]
    },
    {
      "parameters": {
        "jsCode": "// 🏆 Champion Creator - Real distribution functionality with Crystal Lion features\nconst alienFeatures = {\n  crystal_lion_active: true,\n  glass_transformation: 'QUANTUM_ACTIVE',\n  vsmr_frequency: 432,\n  hologram_projection: true\n};\nreturn $input.all().map(item => ({...item, alien_enhanced: true}));"
      },
      "id": "dist-node-061",
      "name": "🏆 Champion Creator",
      "type": "n8n-nodes-base.code",
      "typeVersion": 2,
      "position": [
        1400,
        1700
      ]
    },
    {
      "parameters": {
        "jsCode": "// 💎 Diamond Polisher - Real distribution functionality with Crystal Lion features\nconst alienFeatures = {\n  crystal_lion_active: true,\n  glass_transformation: 'QUANTUM_ACTIVE',\n  vsmr_frequency: 432,\n  hologram_projection: true\n};\nreturn $input.all().map(item => ({...item, alien_enhanced: true}));"
      },
      "id": "dist-node-062",
      "name": "💎 Diamond Polisher",
      "type": "n8n-nodes-base.code",
      "typeVersion": 2,
      "position": [
        1700,
        1700
      ]
    },
    {
      "parameters": {
        "jsCode": "// 🦁 Final Roar - Real distribution functionality with Crystal Lion features\nconst alienFeatures = {\n  crystal_lion_active: true,\n  glass_transformation: 'QUANTUM_ACTIVE',\n  vsmr_frequency: 432,\n  hologram_projection: true\n};\nreturn $input.all().map(item => ({...item, alien_enhanced: true}));"
      },
      "id": "dist-node-063",
      "name": "🦁 Final Roar",
      "type": "n8n-nodes-base.code",
      "typeVersion": 2,
      "position": [
        2000,
        1700
      ]
    },
    {
      "parameters": {
        "jsCode": "// 🌌 Universe Connector - Real distribution functionality with Crystal Lion features\nconst alienFeatures = {\n  crystal_lion_active: true,\n  glass_transformation: 'QUANTUM_ACTIVE',\n  vsmr_frequency: 432,\n  hologram_projection: true\n};\nreturn $input.all().map(item => ({...item, alien_enhanced: true}));"
      },
      "id": "dist-node-064",
      "name": "🌌 Universe Connector",
      "type": "n8n-nodes-base.code",
      "typeVersion": 2,
      "position": [
        2300,
        1700
      ]
    },
    {
      "parameters": {
        "jsCode": "// ⭐ Eternal Success - Real distribution functionality with Crystal Lion features\nconst alienFeatures = {\n  crystal_lion_active: true,\n  glass_transformation: 'QUANTUM_ACTIVE',\n  vsmr_frequency: 432,\n  hologram_projection: true\n};\nreturn $input.all().map(item => ({...item, alien_enhanced: true}));"
      },
      "id": "dist-node-065",
      "name": "⭐ Eternal Success",
      "type": "n8n-nodes-base.code",
      "typeVersion": 2,
      "position": [
        200,
        1900
      ]
    }
  ],
  "connections": {
    "dist-node-001": {
      "main": [
        [
          {
            "node": "dist-node-002",
            "type": "main",
            "index": 0
          }
        ]
      ]
    },
    "dist-node-002": {
      "main": [
        [
          {
            "node": "dist-node-003",
            "type": "main",
            "index": 0
          }
        ]
      ]
    },
    "dist-node-003": {
      "main": [
        [
          {
            "node": "dist-node-004",
            "type": "main",
            "index": 0
          }
        ]
      ]
    },
    "dist-node-004": {
      "main": [
        [
          {
            "node": "dist-node-005",
            "type": "main",
            "index": 0
          }
        ]
      ]
    },
    "dist-node-005": {
      "main": [
        [
          {
            "node": "dist-node-006",
            "type": "main",
            "index": 0
          }
        ]
      ]
    },
    "dist-node-006": {
      "main": [
        [
          {
            "node": "dist-node-007",
            "type": "main",
            "index": 0
          }
        ]
      ]
    },
    "dist-node-007": {
      "main": [
        [
          {
            "node": "dist-node-008",
            "type": "main",
            "index": 0
          }
        ]
      ]
    },
    "dist-node-008": {
      "main": [
        [
          {
            "node": "dist-node-009",
            "type": "main",
            "index": 0
          }
        ]
      ]
    },
    "dist-node-009": {
      "main": [
        [
          {
            "node": "dist-node-010",
            "type": "main",
            "index": 0
          }
        ]
      ]
    },
    "dist-node-010": {
      "main": [
        [
          {
            "node": "dist-node-011",
            "type": "main",
            "index": 0
          }
        ]
      ]
    },
    "dist-node-011": {
      "main": [
        [
          {
            "node": "dist-node-012",
            "type": "main",
            "index": 0
          }
        ]
      ]
    },
    "dist-node-012": {
      "main": [
        [
          {
            "node": "dist-node-013",
            "type": "main",
            "index": 0
          }
        ]
      ]
    },
    "dist-node-013": {
      "main": [
        [
          {
            "node": "dist-node-014",
            "type": "main",
            "index": 0
          }
        ]
      ]
    },
    "dist-node-014": {
      "main": [
        [
          {
            "node": "dist-node-015",
            "type": "main",
            "index": 0
          }
        ]
      ]
    },
    "dist-node-015": {
      "main": [
        [
          {
            "node": "dist-node-016",
            "type": "main",
            "index": 0
          }
        ]
      ]
    },
    "dist-node-016": {
      "main": [
        [
          {
            "node": "dist-node-017",
            "type": "main",
            "index": 0
          }
        ]
      ]
    },
    "dist-node-017": {
      "main": [
        [
          {
            "node": "dist-node-018",
            "type": "main",
            "index": 0
          }
        ]
      ]
    },
    "dist-node-018": {
      "main": [
        [
          {
            "node": "dist-node-019",
            "type": "main",
            "index": 0
          }
        ]
      ]
    },
    "dist-node-019": {
      "main": [
        [
          {
            "node": "dist-node-020",
            "type": "main",
            "index": 0
          }
        ]
      ]
    },
    "dist-node-020": {
      "main": [
        [
          {
            "node": "dist-node-021",
            "type": "main",
            "index": 0
          }
        ]
      ]
    },
    "dist-node-021": {
      "main": [
        [
          {
            "node": "dist-node-022",
            "type": "main",
            "index": 0
          }
        ]
      ]
    },
    "dist-node-022": {
      "main": [
        [
          {
            "node": "dist-node-023",
            "type": "main",
            "index": 0
          }
        ]
      ]
    },
    "dist-node-023": {
      "main": [
        [
          {
            "node": "dist-node-024",
            "type": "main",
            "index": 0
          }
        ]
      ]
    },
    "dist-node-024": {
      "main": [
        [
          {
            "node": "dist-node-025",
            "type": "main",
            "index": 0
          }
        ]
      ]
    },
    "dist-node-025": {
      "main": [
        [
          {
            "node": "dist-node-026",
            "type": "main",
            "index": 0
          }
        ]
      ]
    },
    "dist-node-026": {
      "main": [
        [
          {
            "node": "dist-node-027",
            "type": "main",
            "index": 0
          }
        ]
      ]
    },
    "dist-node-027": {
      "main": [
        [
          {
            "node": "dist-node-028",
            "type": "main",
            "index": 0
          }
        ]
      ]
    },
    "dist-node-028": {
      "main": [
        [
          {
            "node": "dist-node-029",
            "type": "main",
            "index": 0
          }
        ]
      ]
    },
    "dist-node-029": {
      "main": [
        [
          {
            "node": "dist-node-030",
            "type": "main",
            "index": 0
          }
        ]
      ]
    },
    "dist-node-030": {
      "main": [
        [
          {
            "node": "dist-node-031",
            "type": "main",
            "index": 0
          }
        ]
      ]
    },
    "dist-node-031": {
      "main": [
        [
          {
            "node": "dist-node-032",
            "type": "main",
            "index": 0
          }
        ]
      ]
    },
    "dist-node-032": {
      "main": [
        [
          {
            "node": "dist-node-033",
            "type": "main",
            "index": 0
          }
        ]
      ]
    },
    "dist-node-033": {
      "main": [
        [
          {
            "node": "dist-node-034",
            "type": "main",
            "index": 0
          }
        ]
      ]
    },
    "dist-node-034": {
      "main": [
        [
          {
            "node": "dist-node-035",
            "type": "main",
            "index": 0
          }
        ]
      ]
    },
    "dist-node-035": {
      "main": [
        [
          {
            "node": "dist-node-036",
            "type": "main",
            "index": 0
          }
        ]
      ]
    },
    "dist-node-036": {
      "main": [
        [
          {
            "node": "dist-node-037",
            "type": "main",
            "index": 0
          }
        ]
      ]
    },
    "dist-node-037": {
      "main": [
        [
          {
            "node": "dist-node-038",
            "type": "main",
            "index": 0
          }
        ]
      ]
    },
    "dist-node-038": {
      "main": [
        [
          {
            "node": "dist-node-039",
            "type": "main",
            "index": 0
          }
        ]
      ]
    },
    "dist-node-039": {
      "main": [
        [
          {
            "node": "dist-node-040",
            "type": "main",
            "index": 0
          }
        ]
      ]
    },
    "dist-node-040": {
      "main": [
        [
          {
            "node": "dist-node-041",
            "type": "main",
            "index": 0
          }
        ]
      ]
    },
    "dist-node-041": {
      "main": [
        [
          {
            "node": "dist-node-042",
            "type": "main",
            "index": 0
          }
        ]
      ]
    },
    "dist-node-042": {
      "main": [
        [
          {
            "node": "dist-node-043",
            "type": "main",
            "index": 0
          }
        ]
      ]
    },
    "dist-node-043": {
      "main": [
        [
          {
            "node": "dist-node-044",
            "type": "main",
            "index": 0
          }
        ]
      ]
    },
    "dist-node-044": {
      "main": [
        [
          {
            "node": "dist-node-045",
            "type": "main",
            "index": 0
          }
        ]
      ]
    },
    "dist-node-045": {
      "main": [
        [
          {
            "node": "dist-node-046",
            "type": "main",
            "index": 0
          }
        ]
      ]
    },
    "dist-node-046": {
      "main": [
        [
          {
            "node": "dist-node-047",
            "type": "main",
            "index": 0
          }
        ]
      ]
    },
    "dist-node-047": {
      "main": [
        [
          {
            "node": "dist-node-048",
            "type": "main",
            "index": 0
          }
        ]
      ]
    },
    "dist-node-048": {
      "main": [
        [
          {
            "node": "dist-node-049",
            "type": "main",
            "index": 0
          }
        ]
      ]
    },
    "dist-node-049": {
      "main": [
        [
          {
            "node": "dist-node-050",
            "type": "main",
            "index": 0
          }
        ]
      ]
    },
    "dist-node-050": {
      "main": [
        [
          {
            "node": "dist-node-051",
            "type": "main",
            "index": 0
          }
        ]
      ]
    },
    "dist-node-051": {
      "main": [
        [
          {
            "node": "dist-node-052",
            "type": "main",
            "index": 0
          }
        ]
      ]
    },
    "dist-node-052": {
      "main": [
        [
          {
            "node": "dist-node-053",
            "type": "main",
            "index": 0
          }
        ]
      ]
    },
    "dist-node-053": {
      "main": [
        [
          {
            "node": "dist-node-054",
            "type": "main",
            "index": 0
          }
        ]
      ]
    },
    "dist-node-054": {
      "main": [
        [
          {
            "node": "dist-node-055",
            "type": "main",
            "index": 0
          }
        ]
      ]
    },
    "dist-node-055": {
      "main": [
        [
          {
            "node": "dist-node-056",
            "type": "main",
            "index": 0
          }
        ]
      ]
    },
    "dist-node-056": {
      "main": [
        [
          {
            "node": "dist-node-057",
            "type": "main",
            "index": 0
          }
        ]
      ]
    },
    "dist-node-057": {
      "main": [
        [
          {
            "node": "dist-node-058",
            "type": "main",
            "index": 0
          }
        ]
      ]
    },
    "dist-node-058": {
      "main": [
        [
          {
            "node": "dist-node-059",
            "type": "main",
            "index": 0
          }
        ]
      ]
    },
    "dist-node-059": {
      "main": [
        [
          {
            "node": "dist-node-060",
            "type": "main",
            "index": 0
          }
        ]
      ]
    },
    "dist-node-060": {
      "main": [
        [
          {
            "node": "dist-node-061",
            "type": "main",
            "index": 0
          }
        ]
      ]
    },
    "dist-node-061": {
      "main": [
        [
          {
            "node": "dist-node-062",
            "type": "main",
            "index": 0
          }
        ]
      ]
    },
    "dist-node-062": {
      "main": [
        [
          {
            "node": "dist-node-063",
            "type": "main",
            "index": 0
          }
        ]
      ]
    },
    "dist-node-063": {
      "main": [
        [
          {
            "node": "dist-node-064",
            "type": "main",
            "index": 0
          }
        ]
      ]
    }
  }
}